viddur/__init__.py
viddur/__main__.py
viddur/source.py
viddur-0.1.2.dist-info/entry_points.txt
viddur-0.1.2.dist-info/LICENSE
viddur-0.1.2.dist-info/WHEEL
viddur-0.1.2.dist-info/METADATA
viddur-0.1.2.dist-info/RECORD
