Metadata-Version: 2.1
Name: viddur
Version: 0.1.2
Summary: Calculating and viewing the durations of videos.
Home-page: https://github.com/Mahyar24/viddur
License: GPL-3.0-or-later
Keywords: FFprobe,viddur,video duration
Author: Mahyar Mahdavi
Author-email: Mahyar@Mahyar24.com
Requires-Python: >=3.9,<4.0
Classifier: License :: OSI Approved :: GNU General Public License v3 or later (GPLv3+)
Classifier: Programming Language :: Python :: 3
Classifier: Programming Language :: Python :: 3.10
Classifier: Programming Language :: Python :: 3.9
Project-URL: Repository, https://github.com/Mahyar24/viddur
